{
    "in": 8,
    "the": 38,
    "quiet": 1,
    ",": 33,
    "winds": 1,
    "we": 1,
    "pt": 1,
    "hamlet": 1,
    "of": 16,
    "will": 5,
    "ow": 5,
    "'": 13,
    "s": 21,
    "end": 5,
    "a": 16,
    "tale": 7,
    "as": 6,
    "deep": 1,
    "ocean": 5,
    "current": 1,
    "and": 5,
    "old": 3,
    "village": 3,
    "itself": 2,
    "has": 4,
    "": 13,
    "re": 4,
    "surface": 1,
    "d": 2,
    "sending": 1,
    "shiver": 1,
    "down": 1,
    "spine": 1,
    "even": 1,
    "most": 2,
    "season": 1,
    "ed": 4,
    "sea": 3,
    "far": 1,
    "ers": 1,
    ".": 12,
    "on": 5,
    "oc": 1,
    "to": 4,
    "ber": 1,
    "14": 1,
    "20": 1,
    "23": 1,
    "disappearance": 3,
    "pet": 2,
    "er": 3,
    "m": 3,
    "clear": 3,
    "y": 4,
    "fisherman": 2,
    "renowned": 1,
    "for": 3,
    "his": 7,
    "adherence": 1,
    "sustainable": 1,
    "practices": 1,
    "resurrect": 1,
    "echoes": 1,
    "centuries": 1,
    "-": 3,
    "legend": 1,
    "thread": 1,
    "ing": 7,
    "together": 1,
    "past": 1,
    "present": 1,
    "that": 6,
    "span": 1,
    "generations": 1,
    "underscores": 1,
    "ongoing": 1,
    "battle": 1,
    "health": 1,
    "story": 1,
    "begins": 1,
    "sept": 1,
    "ember": 1,
    "17": 1,
    "18": 1,
    "19": 1,
    "when": 1,
    "john": 1,
    "had": 4,
    "dock": 3,
    "name": 1,
    "now": 2,
    "synonymous": 1,
    "with": 3,
    "folklore": 1,
    "vanished": 1,
    "into": 2,
    "water": 1,
    "abyss": 1,
    "goes": 1,
    "was": 1,
    "cosmic": 1,
    "consequence": 1,
    "greed": 1,
    "stark": 1,
    "warning": 1,
    "from": 1,
    "depths": 1,
    "against": 1,
    "over": 1,
    "fish": 1,
    "an": 2,
    "act": 1,
    "would": 1,
    "drain": 1,
    "life": 3,
    "blood": 1,
    "inscribed": 1,
    "same": 1,
    "n": 1,
    "mollusk": 1,
    "communal": 1,
    "memory": 1,
    "became": 1,
    "par": 1,
    "able": 1,
    "urging": 1,
    "future": 1,
    "fishermen": 1,
    "maintain": 1,
    "balance": 1,
    "respect": 1,
    "marine": 1,
    "ecosystem": 1,
    "sustained": 1,
    "them": 1,
    "known": 1,
    "eco": 1,
    "conscious": 1,
    "methods": 1,
    "lived": 1,
    "by": 3,
    "these": 1,
    "teachings": 1,
    "<unk>": 2,
    "\u043e": 3,
    "\u0440": 1,
    "put": 1,
    "net": 1,
    "were": 1,
    "hardly": 1,
    "threat": 1,
    "scales": 1,
    "harmony": 1,
    "\u2013": 1,
    "fact": 1,
    "made": 1,
    "unexpected": 1,
    "vanish": 2,
    "all": 1,
    "more": 2,
    "enigmatic": 1,
    "some": 1,
    "respects": 1,
    "eer": 1,
    "ily": 1,
    "reminiscent": 1,
    "legendary": 1,
    "fate": 1,
    "community": 1,
    "grappling": 1,
    "un": 1,
    "can": 1,
    "ny": 1,
    "parallel": 1,
    "found": 1,
    "restart": 1,
    "dialogue": 1,
    "environmental": 1,
    "stewardship": 1,
    "exacerbated": 1,
    "unexplained": 1,
    "nature": 1,
    "irony": 1,
    "is": 1,
    "not": 3,
    "lost": 1,
    "inhabitants": 1,
    "man": 1,
    "who": 1,
    "spent": 1,
    "champion": 1,
    "cause": 1,
    "should": 1,
    "become": 1,
    "ent": 1,
    "win": 1,
    "its": 2,
    "mysterious": 1,
    "this": 1,
    "event": 1,
    "sparked": 1,
    "resurgence": 1,
    "interest": 1,
    "just": 2,
    "supernatural": 1,
    "whisper": 2,
    "yo": 1,
    "but": 2,
    "importantly": 1,
    "very": 1,
    "real": 1,
    "concerns": 1,
    "conservation": 1,
    "nestle": 1,
    "ce": 1,
    "rule": 1,
    "embrace": 1,
    "bay": 1,
    "stands": 1,
    "at": 1,
    "crossroads": 1,
    "corners": 1,
    "verb": 1,
    "ating": 1,
    "carry": 1,
    "wisdom": 1,
    "result": 1,
    "taken": 1,
    "new": 1,
    "spir": 1,
    "fear": 1,
    "also": 1,
    "action": 1,
    "annual": 1,
    "<sep>": 1,
    "<cls>": 1
}