{
    "in": 7,
    "the": 16,
    "bustling": 1,
    "heart": 2,
    "of": 11,
    "our": 4,
    "small": 1,
    "town": 3,
    ",": 34,
    "a": 12,
    "<unk>": 1,
    "takes": 1,
    "shape": 1,
    ":": 1,
    "wear": 6,
    "able": 6,
    "s": 18,
    "lead": 1,
    "charge": 1,
    "sept": 1,
    "ember": 1,
    "20": 1,
    "23": 1,
    "has": 4,
    "marked": 1,
    "significant": 1,
    "shift": 2,
    "way": 1,
    "we": 1,
    "approach": 1,
    "health": 4,
    "and": 10,
    "fitness": 10,
    "not": 2,
    "just": 6,
    "as": 4,
    "individuals": 1,
    "but": 3,
    "community": 2,
    ".": 16,
    "no": 3,
    "longer": 3,
    "bound": 1,
    "by": 4,
    "cliche": 1,
    "d": 3,
    "narrative": 1,
    "dusty": 1,
    "gym": 1,
    "shoes": 1,
    "analog": 1,
    "scales": 1,
    "now": 2,
    "embraced": 1,
    "an": 2,
    "era": 1,
    "where": 3,
    "technology": 2,
    "reign": 1,
    "supreme": 1,
    "once": 1,
    "-": 6,
    "fa": 1,
    "mili": 1,
    "ar": 1,
    "sight": 1,
    "people": 1,
    "jogging": 1,
    "with": 6,
    "good": 1,
    "old": 1,
    "fashioned": 1,
    "(": 1,
    "card": 1,
    "io": 1,
    ")": 1,
    "monitor": 1,
    "been": 3,
    "replaced": 1,
    "sea": 1,
    "sleek": 1,
    "high": 1,
    "tech": 2,
    "gadget": 1,
    "adorn": 1,
    "ing": 3,
    "wrist": 1,
    "each": 1,
    "silently": 1,
    "communicating": 1,
    "wealth": 1,
    "personal": 4,
    "metric": 1,
    "it": 3,
    "'": 5,
    "about": 3,
    "calories": 1,
    "burned": 1,
    "or": 2,
    "steps": 1,
    "taken": 1,
    ";": 2,
    "these": 2,
    "devices": 2,
    "ranging": 1,
    "from": 2,
    "advanced": 1,
    "smart": 1,
    "watch": 1,
    "es": 2,
    "to": 2,
    "cutting": 1,
    "edge": 1,
    "track": 1,
    "ers": 1,
    "have": 5,
    "swiftly": 1,
    "become": 2,
    "integral": 1,
    "part": 1,
    "routine": 1,
    "they": 2,
    "are": 3,
    "essence": 1,
    "21": 1,
    "st": 1,
    "century": 1,
    "equivalent": 1,
    "having": 1,
    "coach": 1,
    "always": 1,
    "at": 1,
    "ready": 1,
    "whisper": 1,
    "goals": 1,
    "progress": 1,
    "into": 5,
    "ears": 1,
    "enthusiasts": 1,
    "": 7,
    "\"": 6,
    "innovation": 1,
    "proclaimed": 1,
    "local": 1,
    "fanatic": 1,
    "em": 1,
    "ma": 1,
    "gil": 1,
    "is": 1,
    "touch": 1,
    "offer": 1,
    "push": 1,
    "you": 3,
    "enough": 1,
    "know": 1,
    "your": 1,
    "limits": 1,
    "better": 1,
    "than": 1,
    "adapt": 1,
    "like": 3,
    "persistent": 1,
    "yet": 1,
    "encouraging": 1,
    "friend": 1,
    "personalized": 1,
    "workout": 3,
    "plans": 1,
    "sleep": 1,
    "tracking": 1,
    "even": 1,
    "monitoring": 1,
    "rates": 1,
    "evolved": 1,
    "mere": 1,
    "accessories": 1,
    "indispensable": 1,
    "companions": 1,
    "any": 1,
    "cultural": 1,
    "this": 3,
    "trend": 1,
    "doesn": 1,
    "t": 1,
    "exist": 1,
    "vacuum": 1,
    "influence": 3,
    "rs": 4,
    "those": 1,
    "digital": 2,
    "pie": 1,
    "pipe": 1,
    "well": 1,
    "ness": 1,
    "key": 1,
    "players": 1,
    "dict": 1,
    "ating": 1,
    "also": 2,
    "aesthetic": 1,
    "technological": 1,
    "revolution": 1,
    "function": 1,
    "fashion": 1,
    "too": 1,
    "tract": 1,
    "ive": 1,
    "stainless": 1,
    "ste": 1,
    "el": 1,
    "bands": 1,
    "vibrant": 1,
    "silicon": 1,
    "e": 1,
    "strap": 1,
    "status": 1,
    "symbols": 1,
    "sporting": 1,
    "latest": 1,
    "models": 1,
    "turning": 1,
    "sessions": 1,
    "stylish": 1,
    "showcase": 1,
    "@": 1,
    "fit": 1,
    "fusion": 1,
    "ista": 1,
    "setting": 1,
    "trends": 1,
    "ning": 1,
    "new": 1,
    "bling": 1,
    "integrating": 1,
    "effortlessly": 1,
    "style": 1,
    "penchant": 1,
    "for": 1,
    "sharing": 1,
    "amplified": 1,
    "age": 1,
    "social": 1,
    "media": 1,
    "platforms": 1,
    "transformed": 1,
    "virtual": 1,
    "diaries": 1,
    "residents": 1,
    "actively": 1,
    "log": 1,
    "share": 1,
    "their": 1,
    "data": 1,
    "friends": 1,
    "followers": 1,
    "achievement": 1,
    "badge": 1,
    "weekend": 1,
    "records": 1,
    "parade": 1,
    "foster": 1,
    "sense": 1,
    "healthy": 1,
    "competition": 1,
    "scenario": 1,
    "<sep>": 1,
    "<cls>": 1
}