{
    "title": 1,
    ":": 5,
    "the": 23,
    "new": 2,
    "era": 1,
    "of": 10,
    "recycling": 10,
    "from": 1,
    "": 21,
    "el": 5,
    "m": 8,
    "wood": 5,
    "to": 9,
    "empowerment": 1,
    "in": 4,
    "today": 1,
    "'": 21,
    "s": 12,
    "world": 2,
    ",": 31,
    "where": 3,
    "environmental": 4,
    "consciousness": 1,
    "so": 2,
    "ars": 1,
    "higher": 1,
    "than": 1,
    "ever": 1,
    "community": 3,
    "engagement": 1,
    "has": 1,
    "taken": 1,
    "on": 6,
    "a": 13,
    "moral": 1,
    "imperative": 1,
    ".": 14,
    "it": 2,
    "not": 2,
    "just": 3,
    "about": 2,
    "sort": 1,
    "ing": 7,
    "trash": 1,
    "anymore": 1,
    ";": 2,
    "collective": 1,
    "act": 1,
    "that": 3,
    "foster": 1,
    "sense": 1,
    "shared": 2,
    "responsibility": 1,
    "spark": 1,
    "ignited": 1,
    "this": 5,
    "wave": 1,
    "eco": 2,
    "-": 4,
    "ware": 1,
    "ness": 1,
    "was": 1,
    "lit": 1,
    "few": 1,
    "months": 1,
    "ago": 1,
    "sept": 3,
    "ember": 3,
    "10": 1,
    "20": 4,
    "23": 4,
    "marking": 1,
    "inception": 1,
    "organized": 1,
    "programs": 2,
    "these": 1,
    "transcend": 1,
    "beyond": 1,
    "individual": 1,
    "efforts": 2,
    "brought": 1,
    "communities": 1,
    "together": 1,
    "with": 4,
    "common": 1,
    "goal": 1,
    "\u2014": 2,
    "protect": 1,
    "planet": 1,
    "for": 4,
    "future": 1,
    "generations": 1,
    "setting": 1,
    "trend": 1,
    "primary": 2,
    "school": 2,
    "leads": 1,
    "way": 1,
    "among": 1,
    "earliest": 1,
    "proponent": 1,
    "charge": 1,
    "stands": 1,
    "which": 1,
    "termed": 1,
    "15": 1,
    "turning": 1,
    "point": 1,
    "launch": 3,
    "re": 8,
    "cycle": 3,
    "and": 4,
    "learn": 1,
    "program": 1,
    "wasn": 1,
    "t": 2,
    "mere": 1,
    "classroom": 1,
    "learning": 1,
    "student": 1,
    "were": 1,
    "stepping": 1,
    "out": 1,
    "into": 1,
    "became": 1,
    "hands": 1,
    "lesson": 1,
    "principal": 1,
    "mark": 1,
    "tho": 1,
    "mp": 1,
    "son": 1,
    "\"": 4,
    "we": 2,
    "teaching": 1,
    "children": 1,
    "empower": 1,
    "them": 1,
    "become": 1,
    "agents": 1,
    "change": 1,
    "by": 2,
    "blend": 1,
    "education": 1,
    "action": 1,
    "initiative": 4,
    "sparked": 1,
    "vital": 1,
    "conversation": 1,
    "households": 1,
    "demonstrating": 1,
    "even": 2,
    "youngest": 1,
    "citizens": 1,
    "can": 1,
    "contribute": 1,
    "sustainability": 1,
    "visionary": 1,
    "call": 1,
    "aria": 3,
    "gon": 3,
    "zal": 3,
    "ez": 3,
    "all": 3,
    "while": 1,
    "wed": 1,
    "seeds": 1,
    "at": 2,
    "grassroots": 1,
    "an": 1,
    "activist": 1,
    "took": 1,
    "broader": 1,
    "launching": 1,
    "oc": 1,
    "ber": 1,
    "5": 1,
    "movement": 1,
    "aimed": 1,
    "bridge": 1,
    "gap": 1,
    "ensuring": 1,
    "accessibility": 1,
    "regardless": 1,
    "socio": 1,
    "economic": 1,
    "boundaries": 1,
    "cycl": 1,
    "shouldn": 1,
    "be": 1,
    "luxury": 1,
    "but": 1,
    "universal": 1,
    "practice": 1,
    "emphasized": 1,
    "speaking": 1,
    "event": 1,
    "providing": 1,
    "reusable": 1,
    "collection": 1,
    "bin": 1,
    "across": 1,
    "city": 1,
    "hosting": 1,
    "workshops": 1,
    "truly": 1,
    "embodied": 1,
    "spirit": 1,
    "clu": 1,
    "ivity": 1,
    "tech": 2,
    "takes": 1,
    "helm": 1,
    "birth": 1,
    "cyclo": 2,
    "app": 3,
    "simultaneously": 1,
    "enthusiasts": 1,
    "embraced": 1,
    "challenge": 1,
    "unveil": 1,
    "30": 1,
    "innovative": 1,
    "mobile": 1,
    "application": 1,
    "streamlined": 1,
    "guiding": 1,
    "users": 1,
    "what": 1,
    "recycle": 2,
    "rewarding": 1,
    "conscious": 1,
    "behavior": 1,
    "coincided": 1,
    "growing": 1,
    "<sep>": 1,
    "<cls>": 1
}