{
    "": 25,
    "**": 2,
    "t": 3,
    "empt": 1,
    "ing": 3,
    "tales": 1,
    ":": 4,
    "a": 25,
    "southern": 3,
    "dessert": 6,
    "journey": 1,
    "through": 2,
    "time": 1,
    "and": 8,
    "tradition": 2,
    "in": 3,
    "the": 27,
    "heart": 1,
    "of": 14,
    "south": 1,
    ",": 31,
    "s": 21,
    "are": 2,
    "not": 3,
    "just": 1,
    "an": 2,
    "indulgence": 1,
    ";": 2,
    "they": 2,
    "rich": 3,
    "tapes": 1,
    "try": 1,
    "woven": 1,
    "with": 3,
    "stories": 1,
    "traditions": 1,
    "testament": 1,
    "to": 10,
    "region": 1,
    "'": 8,
    "vibrant": 2,
    "cultural": 2,
    "heritage": 3,
    ".": 14,
    "this": 2,
    "article": 1,
    "embark": 1,
    "on": 2,
    "sweet": 1,
    "exploration": 1,
    "uncover": 1,
    "historical": 1,
    "significance": 1,
    "each": 1,
    "treat": 1,
    "is": 7,
    "more": 3,
    "than": 2,
    "mor": 1,
    "sel": 1,
    "\u2014": 5,
    "it": 6,
    "piece": 1,
    "history": 1,
    "living": 1,
    "narrative": 1,
    "that": 3,
    "connects": 1,
    "past": 1,
    "present": 2,
    "*": 6,
    "mississippi": 3,
    "mud": 2,
    "pie": 4,
    "slice": 1,
    "nestle": 1,
    "d": 1,
    "lush": 1,
    "green": 2,
    "ery": 1,
    "ros": 3,
    "sim": 1,
    "mons": 1,
    "name": 1,
    "synonymous": 1,
    "revival": 1,
    "traditional": 1,
    "making": 1,
    "was": 1,
    "oc": 1,
    "ber": 1,
    "3": 1,
    "rd": 1,
    "20": 1,
    "23": 1,
    "began": 1,
    "her": 2,
    "mission": 1,
    "revive": 1,
    "these": 1,
    "classic": 1,
    "recipes": 1,
    "among": 1,
    "most": 1,
    "glorious": 1,
    "creation": 1,
    "concoct": 1,
    "ion": 1,
    "so": 1,
    "decade": 1,
    "nt": 1,
    "seems": 1,
    "breathe": 1,
    "very": 1,
    "essence": 1,
    "state": 2,
    "\u2019": 2,
    "rolling": 1,
    "landscape": 1,
    "pec": 1,
    "ans": 1,
    "hand": 1,
    "pick": 1,
    "ed": 2,
    "from": 1,
    "fertile": 1,
    "grounds": 1,
    "add": 1,
    "crunch": 1,
    "y": 1,
    "texture": 1,
    "while": 1,
    "freshly": 1,
    "churn": 1,
    "butter": 1,
    "brings": 1,
    "out": 1,
    "luxurious": 1,
    "cream": 1,
    "iness": 1,
    "merely": 1,
    "homage": 1,
    "loving": 1,
    "ly": 1,
    "passed": 1,
    "down": 1,
    "generations": 1,
    "according": 1,
    "\"": 2,
    "every": 1,
    "spoon": 1,
    "ful": 1,
    "celebration": 2,
    "our": 3,
    "land": 1,
    "people": 1,
    "resilience": 1,
    "louisiana": 2,
    "king": 3,
    "cake": 5,
    "m": 3,
    "ardi": 3,
    "gra": 3,
    "de": 1,
    "lic": 1,
    "acy": 1,
    "dive": 1,
    "into": 2,
    "world": 1,
    "where": 1,
    "reign": 1,
    "supreme": 1,
    "symbol": 1,
    "unity": 1,
    "luck": 2,
    "bit": 1,
    "mystery": 1,
    "traditionally": 1,
    "baked": 1,
    "for": 1,
    "as": 2,
    "colorful": 1,
    "festivities": 1,
    "themselves": 1,
    "adorned": 1,
    "official": 1,
    "carnival": 1,
    "colors": 1,
    "pur": 1,
    "ple": 1,
    "gold": 1,
    "re": 1,
    "justice": 1,
    "faith": 1,
    "power": 1,
    "respectively": 1,
    "but": 1,
    "icing": 1,
    "makes": 1,
    "unique": 1,
    "hidden": 1,
    "inside": 1,
    "small": 1,
    "rink": 2,
    "et": 1,
    "often": 1,
    "plastic": 1,
    "baby": 1,
    "or": 1,
    "pe": 1,
    "can": 1,
    "waiting": 1,
    "bring": 1,
    "lucky": 1,
    "finder": 1,
    "be": 1,
    "stow": 1,
    "upon": 1,
    "them": 1,
    "responsibility": 1,
    "hosting": 1,
    "next": 1,
    "assuming": 1,
    "course": 1,
    "manage": 1,
    "avoid": 1,
    "un": 1,
    "av": 1,
    "ory": 1,
    "ets": 1,
    "occasionally": 1,
    "thrown": 1,
    "mix": 1,
    "by": 1,
    "mischievous": 1,
    "baker": 1,
    "tennessee": 1,
    "stack": 1,
    "symphony": 1,
    "community": 1,
    "spirit": 1,
    "voyage": 1,
    "<sep>": 1,
    "<cls>": 1
}