{
    "": 19,
    "#": 15,
    "the": 10,
    "mobile": 18,
    "revolution": 1,
    ":": 4,
    "how": 2,
    "s": 17,
    "mes": 13,
    "are": 5,
    "harness": 1,
    "ing": 3,
    "power": 1,
    "of": 10,
    "technology": 5,
    "for": 7,
    "growth": 2,
    "in": 9,
    "a": 10,
    "world": 1,
    "dominated": 1,
    "by": 6,
    "smartphone": 1,
    "and": 12,
    "digital": 4,
    "connectivity": 1,
    ",": 24,
    "it": 2,
    "'": 2,
    "no": 1,
    "surprise": 1,
    "that": 3,
    "has": 3,
    "become": 3,
    "game": 1,
    "change": 1,
    "r": 1,
    "small": 1,
    "medium": 1,
    "enterprises": 1,
    "(": 1,
    ")": 1,
    ".": 17,
    "as": 1,
    "sept": 1,
    "ember": 1,
    "20": 1,
    "23": 1,
    "staggering": 1,
    "8": 1,
    "5%": 1,
    "have": 7,
    "integrated": 2,
    "marketing": 5,
    "into": 2,
    "their": 7,
    "strategies": 2,
    "reflecting": 1,
    "significant": 1,
    "shift": 1,
    "towards": 1,
    "lever": 1,
    "aging": 1,
    "platforms": 4,
    "business": 1,
    "this": 3,
    "article": 1,
    "explores": 1,
    "using": 1,
    "to": 9,
    "enhance": 1,
    "customer": 2,
    "engagement": 4,
    "streamline": 1,
    "transactions": 2,
    "boost": 1,
    "sales": 3,
    "productivity": 1,
    "devices": 2,
    "an": 1,
    "es": 1,
    "cap": 1,
    "able": 3,
    "part": 1,
    "our": 1,
    "daily": 2,
    "lives": 1,
    "average": 1,
    "consumer": 2,
    "now": 2,
    "spends": 1,
    "approximately": 1,
    "3": 1,
    "5": 1,
    "hours": 1,
    "eng": 1,
    "ros": 1,
    "ed": 2,
    "device": 1,
    "consuming": 1,
    "content": 2,
    "social": 3,
    "izing": 3,
    "online": 1,
    "making": 2,
    "purchases": 1,
    "statistic": 1,
    "not": 3,
    "gone": 1,
    "unnoticed": 1,
    "who": 2,
    "adapted": 1,
    "tap": 1,
    "vast": 1,
    "space": 1,
    "most": 1,
    "connecting": 1,
    "directly": 1,
    "with": 2,
    "target": 1,
    "audience": 1,
    "foster": 1,
    "relationships": 1,
    "driving": 2,
    "ways": 2,
    "were": 1,
    "un": 1,
    "im": 1,
    "agin": 1,
    "decade": 1,
    "ago": 1,
    "media": 2,
    "force": 1,
    "proved": 1,
    "be": 1,
    "double": 1,
    "-": 7,
    "ged": 1,
    "sword": 1,
    "hands": 1,
    "like": 1,
    "face": 1,
    "book": 1,
    "twitter": 1,
    "sta": 1,
    "gram": 1,
    "linked": 1,
    "crucial": 1,
    "channels": 1,
    "only": 1,
    "do": 1,
    "these": 1,
    "offer": 1,
    "cost": 1,
    "effective": 1,
    "advertise": 1,
    "products": 1,
    "or": 1,
    "services": 1,
    "but": 2,
    "they": 1,
    "also": 2,
    "provide": 1,
    "valuable": 1,
    "data": 2,
    "on": 1,
    "behavior": 1,
    "patterns": 1,
    "ability": 1,
    "track": 1,
    "is": 3,
    "engaging": 1,
    "when": 1,
    "under": 1,
    "what": 1,
    "circumstances": 1,
    "gold": 1,
    "mine": 1,
    "better": 1,
    "equipped": 1,
    "make": 1,
    "driven": 1,
    "decisions": 1,
    "personal": 1,
    "outreach": 1,
    "efforts": 1,
    "maximize": 1,
    "first": 2,
    "website": 2,
    "design": 3,
    "enhancing": 1,
    "response": 1,
    "growing": 1,
    "dominance": 1,
    "usage": 1,
    "discovered": 1,
    "just": 1,
    "trend": 1,
    "necessity": 1,
    "prior": 1,
    "websites": 1,
    "applications": 1,
    "been": 1,
    "improve": 1,
    "substantial": 1,
    "60%": 1,
    "friendly": 1,
    "designs": 1,
    "facilitate": 1,
    "easy": 1,
    "browsing": 1,
    "quick": 1,
    "information": 1,
    "access": 1,
    "streamlined": 1,
    "purchasing": 1,
    "processes": 1,
    "\u2014": 1,
    "all": 1,
    "which": 1,
    "critical": 1,
    "components": 1,
    "today": 1,
    "fast": 1,
    "paced": 1,
    "marketplace": 1,
    "simplify": 1,
    "payments": 2,
    "loyalty": 2,
    "programs": 2,
    "transformed": 1,
    "transaction": 1,
    "process": 1,
    "utilizing": 1,
    "<sep>": 1,
    "<cls>": 1
}