{
    "": 28,
    "#": 11,
    "the": 36,
    "wise": 1,
    "c": 1,
    "rack": 1,
    "s": 13,
    "of": 25,
    "world": 3,
    ":": 1,
    "unravel": 1,
    "ing": 1,
    "universal": 2,
    "language": 1,
    "trick": 3,
    "ster": 3,
    "tales": 4,
    "in": 15,
    "a": 10,
    "where": 1,
    "diversity": 1,
    "reign": 1,
    "supreme": 1,
    ",": 29,
    "there": 2,
    "is": 2,
    "but": 4,
    "one": 2,
    "constant": 1,
    "\u2014": 1,
    "deep": 1,
    "-": 2,
    "seat": 1,
    "ed": 2,
    "and": 17,
    "fascination": 1,
    "with": 5,
    "narrative": 2,
    "that": 2,
    "revolve": 1,
    "around": 2,
    "tricks": 1,
    "ters": 1,
    ".": 12,
    "from": 2,
    "dense": 1,
    "jungle": 1,
    "fri": 2,
    "ca": 2,
    "to": 4,
    "frost": 1,
    "t": 3,
    "ipped": 1,
    "forests": 1,
    "euro": 2,
    "pe": 2,
    "sweeping": 1,
    "plain": 1,
    "north": 2,
    "america": 2,
    "have": 1,
    "slit": 1,
    "her": 1,
    "tro": 1,
    "ted": 1,
    "leaped": 1,
    "their": 1,
    "way": 1,
    "into": 1,
    "tapes": 1,
    "try": 1,
    "cultural": 1,
    "weaving": 2,
    "together": 1,
    "common": 1,
    "thread": 1,
    "fabric": 1,
    "humanity": 1,
    "art": 2,
    "deceit": 2,
    "wrapped": 1,
    "wisdom": 3,
    "imagine": 1,
    "night": 1,
    "ash": 1,
    "anti": 1,
    "empire": 1,
    "**": 8,
    "an": 5,
    "si": 2,
    "spider": 1,
    "are": 1,
    "told": 1,
    "glowing": 1,
    "ember": 1,
    "figure": 2,
    "so": 1,
    "seemingly": 1,
    "significant": 1,
    "stature": 1,
    "towering": 1,
    "doesn": 1,
    "'": 1,
    "merely": 1,
    "entertain": 1,
    "teaches": 1,
    "his": 3,
    "stories": 2,
    "often": 2,
    "riddled": 1,
    "mischief": 1,
    "cunning": 1,
    "resonate": 1,
    "west": 1,
    "african": 1,
    "eth": 1,
    "os": 1,
    "reflecting": 1,
    "complexity": 1,
    "human": 2,
    "nature": 1,
    "need": 1,
    "for": 2,
    "face": 1,
    "challenges": 1,
    "across": 1,
    "vast": 1,
    "atlantic": 1,
    "heart": 1,
    "story": 1,
    "co": 1,
    "y": 1,
    "ote": 1,
    "unfold": 1,
    "this": 3,
    "character": 2,
    "known": 1,
    "legendary": 1,
    "status": 1,
    "among": 1,
    "native": 1,
    "american": 1,
    "tribes": 1,
    "particularly": 1,
    "pacific": 1,
    "northwest": 1,
    "symbolize": 1,
    "very": 1,
    "essence": 1,
    "fol": 1,
    "ly": 2,
    "severe": 1,
    "consequences": 1,
    "pride": 1,
    "coyote": 1,
    "remind": 1,
    "us": 1,
    "even": 1,
    "most": 3,
    "foolish": 1,
    "actions": 1,
    "can": 2,
    "sometimes": 1,
    "lead": 1,
    "profound": 1,
    "lessons": 1,
    "whimsical": 1,
    "br": 3,
    "er": 3,
    "rabbit": 3,
    "then": 1,
    "whose": 1,
    "echoes": 1,
    "be": 1,
    "heard": 1,
    "laughter": 1,
    "both": 1,
    "children": 1,
    "adults": 1,
    "originating": 1,
    "oral": 1,
    "traditions": 1,
    "cher": 1,
    "oke": 1,
    "e": 1,
    "lore": 1,
    "fusion": 1,
    "european": 1,
    "folklore": 1,
    "ultimate": 1,
    "escape": 1,
    "artist": 1,
    "not": 1,
    "by": 2,
    "might": 1,
    "wit": 2,
    "fascinated": 1,
    "listeners": 1,
    "quick": 1,
    "thinking": 1,
    "ability": 1,
    "out": 1,
    "smart": 1,
    "those": 1,
    "far": 1,
    "larger": 1,
    "more": 1,
    "powerful": 2,
    "emblem": 1,
    "atic": 1,
    "resilience": 1,
    "against": 1,
    "oppression": 1,
    "spirit": 1,
    "survival": 1,
    "remains": 1,
    "beloved": 1,
    "enduring": 1,
    "nal": 1,
    "storytelling": 1,
    "tee": 1,
    "ming": 1,
    "magic": 1,
    "mystery": 1,
    "rey": 1,
    "nard": 1,
    "fox": 1,
    "paint": 1,
    "striking": 1,
    "different": 1,
    "picture": 1,
    "rebellion": 1,
    "dating": 1,
    "back": 1,
    "medieval": 1,
    "times": 1,
    "notably": 1,
    "epic": 1,
    "\"": 2,
    "ro": 1,
    "man": 1,
    "de": 1,
    "ren": 1,
    "mock": 1,
    "expose": 1,
    "greed": 1,
    "<sep>": 1,
    "<cls>": 1
}