{
    "": 17,
    "**": 8,
    "the": 34,
    "sub": 1,
    "a": 17,
    "que": 1,
    "ous": 1,
    "sovereign": 2,
    "emerge": 1,
    "s": 10,
    ":": 1,
    "at": 9,
    "lan": 8,
    "tis": 6,
    ",": 25,
    "force": 1,
    "for": 1,
    "evolutionary": 1,
    "environmental": 3,
    "ism": 1,
    "in": 9,
    "world": 5,
    "rife": 1,
    "with": 7,
    "peril": 1,
    "of": 19,
    "climate": 2,
    "change": 2,
    "emergence": 1,
    "new": 1,
    "player": 1,
    "on": 2,
    "global": 1,
    "stage": 1,
    "has": 3,
    "sent": 1,
    "ripple": 1,
    "through": 1,
    "corridor": 1,
    "power": 1,
    "deeper": 1,
    "than": 1,
    "any": 2,
    "could": 1,
    "have": 2,
    "imagined": 1,
    ".": 12,
    "under": 2,
    "sea": 1,
    "kingdom": 2,
    "once": 1,
    "subject": 1,
    "mythology": 1,
    "and": 5,
    "speculation": 1,
    "declared": 3,
    "its": 3,
    "independence": 1,
    "stunning": 1,
    "announcement": 2,
    "oc": 1,
    "to": 7,
    "ber": 1,
    "14": 1,
    "20": 1,
    "23": 1,
    "king": 3,
    "tri": 3,
    "ton": 3,
    "us": 3,
    "regal": 1,
    "ruler": 2,
    "this": 3,
    "mysterious": 1,
    "underwater": 2,
    "realm": 2,
    "made": 1,
    "revel": 1,
    "atory": 1,
    "statement": 1,
    "united": 2,
    "nations": 2,
    "turning": 1,
    "spotlight": 1,
    "international": 1,
    "community": 1,
    "onto": 1,
    "technological": 1,
    "ly": 2,
    "advanced": 1,
    "nation": 3,
    "purpose": 1,
    "born": 1,
    "amidst": 1,
    "waves": 1,
    "shrouded": 1,
    "intrigue": 1,
    "ancient": 1,
    "lore": 2,
    "stepped": 1,
    "out": 1,
    "from": 2,
    "depths": 3,
    "stake": 1,
    "claim": 1,
    "as": 2,
    "an": 2,
    "independent": 1,
    "state": 1,
    "by": 3,
    "was": 1,
    "met": 1,
    "we": 3,
    "skepticism": 1,
    "equal": 1,
    "measure": 1,
    "last": 1,
    "vest": 1,
    "ige": 1,
    "human": 1,
    "society": 1,
    "yet": 1,
    "be": 1,
    "fully": 1,
    "explored": 1,
    "modern": 1,
    "age": 3,
    "is": 4,
    "not": 3,
    "only": 1,
    "real": 1,
    "thriving": 1,
    "but": 3,
    "one": 1,
    "that": 5,
    "boasts": 1,
    "technology": 2,
    "far": 1,
    "beyond": 1,
    "ken": 1,
    "mainland": 1,
    "civilization": 1,
    "\"": 6,
    "hidden": 1,
    "over": 2,
    "his": 2,
    "voice": 1,
    "re": 1,
    "son": 1,
    "ating": 1,
    "confidence": 1,
    "who": 1,
    "understands": 1,
    "potential": 1,
    "domain": 1,
    "aim": 1,
    "share": 1,
    "our": 1,
    "discoveries": 1,
    "condition": 1,
    "respect": 1,
    "non": 1,
    "-": 2,
    "ne": 1,
    "go": 1,
    "ti": 1,
    "able": 2,
    "part": 1,
    "agreement": 1,
    "environment": 2,
    "al": 1,
    "concerns": 1,
    "ga": 1,
    "what": 1,
    "drove": 1,
    "enigmatic": 1,
    "shed": 1,
    "centuries": 1,
    "old": 1,
    "cloak": 1,
    "secrecy": 1,
    "?": 1,
    "answer": 1,
    "lies": 1,
    "merely": 1,
    "political": 1,
    "maneuver": 1,
    "ing": 2,
    "very": 1,
    "foundations": 1,
    "upon": 1,
    "which": 1,
    "thrive": 1,
    "\u2014": 1,
    "health": 1,
    "\u2019": 1,
    "ocean": 1,
    "touched": 1,
    "deeply": 1,
    "plight": 1,
    "rav": 1,
    "surface": 2,
    "te": 1,
    "ans": 1,
    "watched": 1,
    "concern": 1,
    "pollution": 1,
    "fish": 1,
    "threaten": 1,
    "delicate": 1,
    "balance": 1,
    "their": 1,
    "own": 1,
    "ecosystem": 1,
    "are": 1,
    "connected": 1,
    "ways": 1,
    "many": 1,
    "might": 1,
    "fat": 1,
    "hom": 1,
    "ca": 1,
    "ps": 1,
    "o": 1,
    "th": 2,
    "all": 3,
    "asa": 2,
    "t": 1,
    "ean": 1,
    "ambassador": 1,
    "figure": 1,
    "po": 1,
    "ise": 1,
    "grace": 1,
    "ming": 1,
    "led": 1,
    "dom": 1,
    "it": 1,
    "will": 1,
    "pivotal": 1,
    "promoting": 1,
    "vision": 1,
    "sharing": 1,
    "cherish": 1,
    "es": 1,
    "earth": 1,
    "'": 1,
    "above": 1,
    "green": 1,
    "revolution": 1,
    "haven": 1,
    "innovation": 1,
    "always": 1,
    "<sep>": 1,
    "<cls>": 1
}