{
    "title": 1,
    ":": 2,
    "the": 34,
    "critical": 4,
    "pulse": 2,
    "of": 18,
    "urban": 2,
    "transportation": 5,
    "lessons": 2,
    "from": 2,
    "great": 1,
    "out": 2,
    "ages": 2,
    "20": 4,
    "23": 4,
    "in": 6,
    "heart": 1,
    "21": 1,
    "st": 1,
    "century": 1,
    ",": 28,
    "cities": 2,
    "around": 1,
    "globe": 1,
    "with": 8,
    "energy": 1,
    "progress": 1,
    "largely": 1,
    "thru": 1,
    "mm": 1,
    "ing": 1,
    "along": 1,
    "to": 8,
    "reliable": 2,
    "rhythm": 1,
    "their": 1,
    "networks": 2,
    ".": 21,
    "but": 4,
    "year": 1,
    "will": 1,
    "be": 2,
    "forever": 1,
    "etched": 1,
    "memory": 1,
    "as": 4,
    "a": 11,
    "crucial": 2,
    "wake": 1,
    "-": 4,
    "up": 1,
    "call": 1,
    "for": 6,
    "planners": 1,
    "and": 9,
    "emergency": 6,
    "management": 1,
    "teams": 1,
    "on": 3,
    "": 3,
    "oc": 1,
    "ber": 1,
    "17": 1,
    "metro": 4,
    "city": 5,
    "lay": 1,
    "paralyzed": 1,
    "its": 3,
    "bustling": 3,
    "system": 2,
    "came": 1,
    "complete": 1,
    "halt": 1,
    "then": 1,
    "no": 1,
    "ve": 1,
    "mber": 1,
    "4": 1,
    "coast": 2,
    "ville": 2,
    "experienced": 1,
    "eer": 2,
    "ily": 1,
    "similar": 1,
    "scenario": 1,
    "this": 2,
    "time": 2,
    "due": 1,
    "software": 2,
    "glitch": 2,
    "that": 2,
    "brought": 2,
    "entire": 1,
    "transit": 1,
    "grinding": 1,
    "standstill": 1,
    "these": 2,
    "events": 1,
    "not": 1,
    "only": 1,
    "importance": 1,
    "contingency": 2,
    "planning": 2,
    "into": 4,
    "sharp": 1,
    "relief": 1,
    "also": 1,
    "highlighted": 1,
    "need": 2,
    "robust": 1,
    "resilient": 1,
    "infrastructure": 1,
    "effective": 1,
    "response": 3,
    "'": 3,
    "s": 7,
    "grim": 1,
    "day": 2,
    "began": 1,
    "any": 1,
    "other": 1,
    "morning": 2,
    "commute": 1,
    "life": 2,
    "by": 1,
    "mid": 1,
    "sudden": 1,
    "power": 1,
    "failure": 2,
    "had": 1,
    "cast": 1,
    "shadow": 1,
    "over": 1,
    "arteries": 1,
    "usually": 1,
    "platforms": 1,
    "transformed": 1,
    "cavern": 1,
    "iness": 1,
    "echoing": 1,
    "announcements": 1,
    "murmur": 1,
    "panic": 2,
    "stricken": 1,
    "voices": 1,
    "despite": 1,
    "quick": 1,
    "action": 1,
    "services": 2,
    "timely": 2,
    "information": 2,
    "dissemination": 1,
    "led": 2,
    "confusion": 1,
    "chaos": 2,
    "passengers": 2,
    "stranded": 2,
    "frustrated": 1,
    "were": 2,
    "left": 2,
    "grapple": 1,
    "uncertainty": 1,
    "scramble": 1,
    "alternative": 3,
    "routes": 1,
    "home": 1,
    "it": 2,
    "was": 5,
    "an": 1,
    "unsettling": 1,
    "reminder": 1,
    "how": 1,
    "vulnerable": 1,
    "such": 1,
    "systems": 2,
    "can": 1,
    "just": 1,
    "weeks": 1,
    "later": 1,
    "echoed": 1,
    "same": 1,
    "theme": 1,
    "albeit": 1,
    "own": 1,
    "twist": 1,
    "culprit": 1,
    "turning": 2,
    "what": 1,
    "should": 1,
    "have": 1,
    "been": 1,
    "routine": 1,
    "logistical": 1,
    "nightmare": 1,
    "buses": 1,
    "trains": 1,
    "remained": 1,
    "idle": 1,
    "mobility": 1,
    "ecosystem": 1,
    "crumb": 1,
    "under": 1,
    "weight": 1,
    "un": 1,
    "fore": 1,
    "een": 1,
    "once": 1,
    "again": 1,
    "shortcomings": 1,
    "laid": 1,
    "bare": 1,
    "dark": 1,
    "struggling": 1,
    "absorb": 1,
    "influx": 1,
    "commuter": 1,
    "incidents": 1,
    "provided": 1,
    "stark": 1,
    "obvious": 2,
    "one": 2,
    "\u2014": 2,
    "line": 1,
    "functioning": 1,
    "less": 1,
    "equally": 1,
    "important": 1,
    "spotlight": 1,
    "effectiveness": 1,
    "strategies": 1,
    "deliver": 1,
    "ance": 1,
    "during": 1,
    "is": 1,
    "maintaining": 1,
    "order": 1,
    "public": 1,
    "trust": 1,
    "however": 1,
    "when": 1,
    "crisis": 1,
    "hit": 1,
    "apparent": 1,
    "often": 1,
    "f": 1,
    "alter": 1,
    "providing": 1,
    "updates": 1,
    "small": 1,
    "ripple": 1,
    "tidal": 1,
    "waves": 1,
    "silver": 1,
    "lining": 1,
    "emerged": 1,
    "potential": 1,
    "solutions": 1,
    "both": 1,
    "bike": 1,
    "sharing": 1,
    "programs": 1,
    "became": 1,
    "makeshift": 1,
    "heroes": 1,
    "<sep>": 1,
    "<cls>": 1
}