{
    "": 21,
    "**": 8,
    "the": 29,
    "invisible": 1,
    "life": 2,
    "line": 2,
    ":": 2,
    "telecommunicati": 2,
    "on": 5,
    "in": 6,
    "wake": 2,
    "of": 20,
    "disasters": 2,
    "and": 10,
    "crises": 2,
    "tro": 1,
    "duction": 1,
    "natural": 1,
    "unprecedented": 1,
    "pose": 1,
    "unique": 1,
    "challenges": 1,
    "that": 7,
    "test": 1,
    "resilience": 1,
    "world": 2,
    "'": 3,
    "s": 6,
    "infrastructure": 2,
    ".": 16,
    "among": 1,
    "critical": 1,
    "lines": 1,
    "are": 1,
    "often": 1,
    "disrupted": 1,
    ",": 25,
    "swift": 1,
    "restoration": 1,
    "improvisation": 1,
    "networks": 1,
    "is": 3,
    "essential": 1,
    "for": 1,
    "timely": 1,
    "response": 1,
    "coordination": 1,
    "community": 3,
    "healing": 1,
    "this": 2,
    "article": 1,
    "explores": 1,
    "recent": 1,
    "instances": 1,
    "when": 1,
    "precious": 2,
    "link": 2,
    "was": 7,
    "maintained": 1,
    "demonstrating": 1,
    "importance": 1,
    "communication": 3,
    "face": 1,
    "daunting": 1,
    "forces": 1,
    "nature": 2,
    "*": 6,
    "thal": 2,
    "assa": 2,
    "quake": 1,
    "rumbling": 1,
    "aftermath": 1,
    "shaken": 1,
    "by": 2,
    "call": 1,
    "cows": 2,
    "oc": 1,
    "to": 7,
    "ber": 1,
    "15": 1,
    "20": 2,
    "23": 2,
    "ground": 1,
    "beneath": 1,
    "stirred": 1,
    "with": 3,
    "fury": 2,
    "unleash": 1,
    "ing": 2,
    "a": 14,
    "magnitude": 1,
    "7": 1,
    "9": 1,
    "earthquake": 1,
    "had": 4,
    "residents": 1,
    "wondering": 1,
    "if": 1,
    "their": 1,
    "tilted": 1,
    "off": 1,
    "its": 3,
    "axis": 1,
    "tremor": 1,
    "claimed": 1,
    "lives": 2,
    "physical": 2,
    "structures": 1,
    "but": 2,
    "eyes": 1,
    "survivors": 1,
    "something": 1,
    "far": 1,
    "more": 2,
    "missing": 1,
    "-": 2,
    "voice": 1,
    "hope": 2,
    "sol": 1,
    "ace": 1,
    "simple": 1,
    "hello": 1,
    "amidst": 1,
    "chaos": 1,
    "heroes": 1,
    "like": 1,
    "jam": 1,
    "es": 1,
    "pf": 2,
    "ie": 2,
    "ffer": 2,
    "emerged": 1,
    "not": 2,
    "cap": 1,
    "e": 1,
    "tool": 1,
    "box": 1,
    "one": 1,
    "those": 2,
    "un": 1,
    "ung": 1,
    "figures": 1,
    "who": 3,
    "ensured": 1,
    "than": 1,
    "just": 2,
    "signal": 1,
    "relay": 1,
    "ed": 3,
    ";": 2,
    "he": 1,
    "conduit": 1,
    "within": 1,
    "48": 1,
    "almost": 2,
    "miraculous": 1,
    "ly": 3,
    "brief": 1,
    "hours": 1,
    "temporary": 1,
    "cell": 1,
    "towers": 1,
    "known": 1,
    "as": 4,
    "cells": 1,
    "wheels": 1,
    "(": 1,
    "co": 1,
    "ws": 1,
    ")": 1,
    "stood": 1,
    "firm": 1,
    "re": 1,
    "establish": 1,
    "threads": 1,
    "been": 1,
    "merciless": 1,
    "snatched": 1,
    "away": 1,
    "they": 1,
    "echoed": 1,
    "words": 1,
    "car": 1,
    "o": 1,
    "ken": 1,
    "ned": 1,
    "y": 1,
    "once": 1,
    "reflected": 1,
    "\"": 2,
    "powerful": 1,
    "way": 1,
    "build": 1,
    "relationships": 1,
    "technological": 1,
    "imposing": 1,
    "yet": 1,
    "symbolic": 1,
    "mankind": 1,
    "adapt": 1,
    "ability": 1,
    "formed": 1,
    "new": 2,
    "vip": 1,
    "lower": 1,
    "divi": 1,
    "de": 1,
    "network": 3,
    "united": 1,
    "felt": 1,
    "isolated": 1,
    "fur": 1,
    "ies": 1,
    "mother": 1,
    "elo": 3,
    "ise": 3,
    "\u2019": 1,
    "wrath": 1,
    "stars": 1,
    "hurricane": 1,
    "which": 1,
    "barrel": 1,
    "into": 1,
    "mont": 1,
    "al": 1,
    "ban": 1,
    "sept": 1,
    "ember": 1,
    "21": 1,
    "left": 1,
    "desolate": 1,
    "landscape": 1,
    "debris": 1,
    "disconnected": 1,
    "storm": 1,
    "scars": 1,
    "were": 1,
    "battered": 1,
    "struggled": 1,
    "gather": 1,
    "fragments": 1,
    "functioning": 1,
    "society": 1,
    "began": 1,
    "arduous": 1,
    "journey": 1,
    "recovery": 1,
    "strategy": 1,
    "devised": 1,
    "bypass": 1,
    "rav": 1,
    "ages": 1,
    "mesh": 1,
    "answer": 1,
    "solution": 1,
    "ingenious": 1,
    "it": 2,
    "necessary": 1,
    "allowed": 1,
    "fragmented": 1,
    "service": 1,
    "areas": 1,
    "connect": 1,
    "communicate": 1,
    "performing": 1,
    "an": 1,
    "magical": 1,
    "operation": 1,
    "corrupt": 1,
    "so": 1,
    "<sep>": 1,
    "<cls>": 1
}